odoo/addons/shopinvader_search_engine/README.rst
odoo/addons/shopinvader_search_engine/__init__.py
odoo/addons/shopinvader_search_engine/__manifest__.py
odoo/addons/shopinvader_search_engine/data/ir_export_product.xml
odoo/addons/shopinvader_search_engine/i18n/shopinvader_search_engine.pot
odoo/addons/shopinvader_search_engine/models/__init__.py
odoo/addons/shopinvader_search_engine/models/se_index.py
odoo/addons/shopinvader_search_engine/models/shopinvader_backend.py
odoo/addons/shopinvader_search_engine/models/shopinvader_category.py
odoo/addons/shopinvader_search_engine/models/shopinvader_variant.py
odoo/addons/shopinvader_search_engine/readme/CONFIGURATION.rst
odoo/addons/shopinvader_search_engine/readme/CONTRIBUTORS.rst
odoo/addons/shopinvader_search_engine/readme/CREDITS.rst
odoo/addons/shopinvader_search_engine/readme/DESCRIPTION.rst
odoo/addons/shopinvader_search_engine/readme/HISTORY.rst
odoo/addons/shopinvader_search_engine/readme/ROADMAP.rst
odoo/addons/shopinvader_search_engine/readme/USAGE.rst
odoo/addons/shopinvader_search_engine/static/description/index.html
odoo/addons/shopinvader_search_engine/tests/__init__.py
odoo/addons/shopinvader_search_engine/tests/test_action_server.py
odoo/addons/shopinvader_search_engine/tests/test_delete_product.py
odoo/addons/shopinvader_search_engine/views/shopinvader_backend_view.xml
odoo/addons/shopinvader_search_engine/views/shopinvader_category_view.xml
odoo/addons/shopinvader_search_engine/views/shopinvader_variant_view.xml
odoo13_addon_shopinvader_search_engine-13.0.2.1.0.dist-info/METADATA
odoo13_addon_shopinvader_search_engine-13.0.2.1.0.dist-info/WHEEL
odoo13_addon_shopinvader_search_engine-13.0.2.1.0.dist-info/top_level.txt
odoo13_addon_shopinvader_search_engine-13.0.2.1.0.dist-info/RECORD
