Metadata-Version: 2.1
Name: odoo13-addon-shopinvader-search-engine
Version: 13.0.2.1.0
Summary: Shopinvader Catalog Search Engine Connector
Home-page: https://github.com/shopinvader/odoo-shopinvader
Author: Akretion
License: AGPL-3
Platform: UNKNOWN
Classifier: Programming Language :: Python
Classifier: Framework :: Odoo
Classifier: License :: OSI Approved :: GNU Affero General Public License v3
Classifier: Development Status :: 5 - Production/Stable
Requires-Python: >=3.5
Requires-Dist: odoo13-addon-base-technical-user
Requires-Dist: odoo13-addon-connector-search-engine
Requires-Dist: odoo13-addon-shopinvader
Requires-Dist: odoo (<13.1dev,>=13.0a)
